{
	"id": "17627b93-b244-4be8-bfb8-c91b15f5130f",
	"name": "PetInformation",
	"values": [
		{
			"key": "randomId",
			"value": "",
			"type": "any",
			"enabled": true
		},
		{
			"key": "randomCategoryId",
			"value": "",
			"type": "any",
			"enabled": true
		},
		{
			"key": "randomTagId1",
			"value": "",
			"type": "any",
			"enabled": true
		},
		{
			"key": "randomTagId2",
			"value": "",
			"type": "any",
			"enabled": true
		},
		{
			"key": "randomName",
			"value": "",
			"type": "any",
			"enabled": true
		},
		{
			"key": "randomCategoryName",
			"value": "",
			"type": "any",
			"enabled": true
		},
		{
			"key": "randomTagName1",
			"value": "",
			"type": "any",
			"enabled": true
		},
		{
			"key": "randomTagName2",
			"value": "",
			"type": "any",
			"enabled": true
		},
		{
			"key": "randomPhotoUrl1",
			"value": "",
			"type": "any",
			"enabled": true
		},
		{
			"key": "randomPhotoUrl2",
			"value": "",
			"type": "any",
			"enabled": true
		},
		{
			"key": "petId",
			"value": "",
			"type": "any",
			"enabled": true
		},
		{
			"key": "username",
			"value": "Musa",
			"type": "default",
			"enabled": true
		},
		{
			"key": "password",
			"value": "Afzaal123!!",
			"type": "default",
			"enabled": true
		}
	],
	"_postman_variable_scope": "environment",
	"_postman_exported_at": "2024-11-25T10:11:54.279Z",
	"_postman_exported_using": "Postman/11.20.0"
}